hexkit/__init__.py
hexkit/__main__.py
hexkit/base.py
hexkit/config.py
hexkit/correlation.py
hexkit/custom_types.py
hexkit/log.py
hexkit/opentelemetry.py
hexkit/py.typed
hexkit/utils.py
hexkit/protocols/__init__.py
hexkit/protocols/dao.py
hexkit/protocols/daopub.py
hexkit/protocols/daosub.py
hexkit/protocols/eventpub.py
hexkit/protocols/eventsub.py
hexkit/protocols/kvstore.py
hexkit/protocols/objstorage.py
hexkit/providers/__init__.py
hexkit/providers/akafka/__init__.py
hexkit/providers/akafka/config.py
hexkit/providers/akafka/testcontainer.py
hexkit/providers/akafka/testutils.py
hexkit/providers/akafka/provider/__init__.py
hexkit/providers/akafka/provider/daosub.py
hexkit/providers/akafka/provider/eventpub.py
hexkit/providers/akafka/provider/eventsub.py
hexkit/providers/akafka/provider/utils.py
hexkit/providers/mongodb/__init__.py
hexkit/providers/mongodb/config.py
hexkit/providers/mongodb/testutils.py
hexkit/providers/mongodb/migrations/__init__.py
hexkit/providers/mongodb/migrations/_manager.py
hexkit/providers/mongodb/migrations/_utils.py
hexkit/providers/mongodb/migrations/helpers.py
hexkit/providers/mongodb/provider/__init__.py
hexkit/providers/mongodb/provider/client.py
hexkit/providers/mongodb/provider/dao.py
hexkit/providers/mongodb/provider/kvstore.py
hexkit/providers/mongodb/provider/utils.py
hexkit/providers/mongokafka/__init__.py
hexkit/providers/mongokafka/config.py
hexkit/providers/mongokafka/testutils.py
hexkit/providers/mongokafka/provider/__init__.py
hexkit/providers/mongokafka/provider/daopub.py
hexkit/providers/mongokafka/provider/persistent_pub.py
hexkit/providers/redis/__init__.py
hexkit/providers/redis/config.py
hexkit/providers/redis/testutils.py
hexkit/providers/redis/provider/__init__.py
hexkit/providers/redis/provider/client.py
hexkit/providers/redis/provider/kvstore.py
hexkit/providers/s3/__init__.py
hexkit/providers/s3/provider.py
hexkit/providers/s3/test_files/__init__.py
hexkit/providers/s3/test_files/test_file1.yaml
hexkit-7.3.0.dist-info/licenses/LICENSE
hexkit-7.3.0.dist-info/METADATA
hexkit-7.3.0.dist-info/WHEEL
hexkit-7.3.0.dist-info/top_level.txt
hexkit-7.3.0.dist-info/RECORD
