Metadata-Version: 2.4
Name: hexkit
Version: 7.3.0
Summary: A Toolkit for Building Microservices using the Hexagonal Architecture
Author-email: "German Human Genome Phenome Archive (GHGA)" <contact@ghga.de>
License: Apache 2.0
Project-URL: Repository, https://github.com/ghga-de/hexkit
Classifier: Development Status :: 5 - Production/Stable
Classifier: Operating System :: POSIX :: Linux
Classifier: Programming Language :: Python :: 3.10
Classifier: Programming Language :: Python :: 3.11
Classifier: Programming Language :: Python :: 3.12
Classifier: Programming Language :: Python :: 3.13
Classifier: License :: OSI Approved :: Apache Software License
Classifier: Topic :: Internet :: WWW/HTTP :: HTTP Servers
Classifier: Topic :: Software Development :: Libraries
Classifier: Intended Audience :: Developers
Requires-Python: >=3.10
License-File: LICENSE
Requires-Dist: opentelemetry-api<2,>=1.39
Requires-Dist: pydantic<3,>=2.12
Requires-Dist: pydantic_settings<3,>=2.12
Requires-Dist: PyYAML<7,>=6
Provides-Extra: akafka
Requires-Dist: aiokafka[lz4,snappy,zstd]~=0.13.0; extra == "akafka"
Requires-Dist: jsonschema<5,>=4.25; extra == "akafka"
Provides-Extra: s3
Requires-Dist: boto3<2,>=1.42; extra == "s3"
Requires-Dist: botocore<2,>=1.42; extra == "s3"
Provides-Extra: mongodb
Requires-Dist: pymongo<5,>=4.15; extra == "mongodb"
Provides-Extra: redis
Requires-Dist: redis<8,>=7.1; extra == "redis"
Provides-Extra: opentelemetry-base
Requires-Dist: opentelemetry-sdk<2,>=1.39.1; extra == "opentelemetry-base"
Requires-Dist: opentelemetry-exporter-otlp<2,>=1.39.1; extra == "opentelemetry-base"
Requires-Dist: opentelemetry-instrumentation>=0.60b1; extra == "opentelemetry-base"
Requires-Dist: opentelemetry-instrumentation-httpx>=0.60b1; extra == "opentelemetry-base"
Requires-Dist: opentelemetry-distro>=0.60b1; extra == "opentelemetry-base"
Provides-Extra: opentelemetry-akafka
Requires-Dist: hexkit[opentelemetry-base]; extra == "opentelemetry-akafka"
Requires-Dist: hexkit[akafka]; extra == "opentelemetry-akafka"
Requires-Dist: opentelemetry-instrumentation-aiokafka>=0.60b1; extra == "opentelemetry-akafka"
Provides-Extra: opentelemetry-mongodb
Requires-Dist: hexkit[opentelemetry-base]; extra == "opentelemetry-mongodb"
Requires-Dist: hexkit[mongodb]; extra == "opentelemetry-mongodb"
Requires-Dist: opentelemetry-instrumentation-pymongo>=0.60b1; extra == "opentelemetry-mongodb"
Provides-Extra: opentelemetry-fastapi
Requires-Dist: hexkit[opentelemetry-base]; extra == "opentelemetry-fastapi"
Requires-Dist: opentelemetry-instrumentation-fastapi>=0.60b1; extra == "opentelemetry-fastapi"
Provides-Extra: opentelemetry-s3
Requires-Dist: hexkit[opentelemetry-base]; extra == "opentelemetry-s3"
Requires-Dist: hexkit[s3]; extra == "opentelemetry-s3"
Requires-Dist: opentelemetry-instrumentation-botocore>=0.60b1; extra == "opentelemetry-s3"
Provides-Extra: opentelemetry-redis
Requires-Dist: hexkit[opentelemetry-base]; extra == "opentelemetry-redis"
Requires-Dist: hexkit[redis]; extra == "opentelemetry-redis"
Requires-Dist: opentelemetry-instrumentation-redis>=0.60b1; extra == "opentelemetry-redis"
Provides-Extra: opentelemetry
Requires-Dist: hexkit[opentelemetry-akafka]; extra == "opentelemetry"
Requires-Dist: hexkit[opentelemetry-mongodb]; extra == "opentelemetry"
Requires-Dist: hexkit[opentelemetry-fastapi]; extra == "opentelemetry"
Requires-Dist: hexkit[opentelemetry-s3]; extra == "opentelemetry"
Provides-Extra: test-akafka
Requires-Dist: hexkit[akafka]; extra == "test-akafka"
Requires-Dist: testcontainers[kafka]<5,>=4.13; extra == "test-akafka"
Provides-Extra: test-s3
Requires-Dist: hexkit[s3]; extra == "test-s3"
Requires-Dist: testcontainers<5,>=4.13; extra == "test-s3"
Provides-Extra: test-mongodb
Requires-Dist: hexkit[mongodb]; extra == "test-mongodb"
Requires-Dist: testcontainers[mongo]<5,>=4.13; extra == "test-mongodb"
Provides-Extra: test-redis
Requires-Dist: hexkit[redis]; extra == "test-redis"
Requires-Dist: testcontainers[redis]<5,>=4.13; extra == "test-redis"
Provides-Extra: test
Requires-Dist: hexkit[test-akafka,test-mongodb,test-s3]; extra == "test"
Provides-Extra: all
Requires-Dist: hexkit[test]; extra == "all"
Requires-Dist: hexkit[opentelemetry]; extra == "all"
Dynamic: license-file
